cupless/__init__.py
cupless/main.py
cupless/paper.py
cupless-1.1.0.dist-info/METADATA
cupless-1.1.0.dist-info/WHEEL
cupless-1.1.0.dist-info/entry_points.txt
cupless-1.1.0.dist-info/top_level.txt
cupless-1.1.0.dist-info/RECORD
