Metadata-Version: 2.4
Name: cupless
Version: 1.1.0
Summary: A Linux command-line wrapper to print from the command-line without cups
Author-email: "@readwithai" <talwrii@github.com>
Project-URL: Homepage, https://github.com/talwrii/cupless
